{"username":"MoonBoy","displayName":"MoonBoy","avatarUrl":"https://drama.gg/assets/avatars/JiexzIRk6xVKK25B.png","slug":"MoonBoy","joinTime":"2021-04-19T05:57:08+00:00","discussionCount":0,"commentCount":12,"canEdit":false,"canDelete":false,"lastSeenAt":"2021-06-18T04:26:43+00:00","canSuspend":false,"canEditPolls":false,"canStartPolls":false,"canSelfEditPolls":false,"canVotePolls":false,"cover":null,"cover_thumbnail":null,"canSetProfileCover":false,"canEditOwnNickname":false,"bio":"A boy from moon","canViewBio":true,"canEditBio":false}