{"username":"DEAD","displayName":"DEAD","avatarUrl":"https://drama.gg/assets/avatars/ITk5xhdlO9hqS1HL.png","slug":"DEAD","joinTime":"2021-05-25T01:52:12+00:00","discussionCount":0,"commentCount":0,"canEdit":false,"canDelete":false,"lastSeenAt":"2021-05-25T15:15:08+00:00","canSuspend":false,"canEditPolls":false,"canStartPolls":false,"canSelfEditPolls":false,"canVotePolls":false,"cover":null,"cover_thumbnail":null,"canSetProfileCover":false,"canEditOwnNickname":false,"bio":null,"canViewBio":true,"canEditBio":false}