{"username":"EclipseClient","displayName":"EclipseClient","avatarUrl":"https://drama.gg/assets/avatars/NeX4elaASVc4MNjn.png","slug":"EclipseClient","joinTime":"2021-09-06T07:58:44+00:00","discussionCount":0,"commentCount":30,"canEdit":false,"canDelete":false,"lastSeenAt":"2021-09-14T01:50:23+00:00","canSuspend":false,"canEditPolls":false,"canStartPolls":false,"canSelfEditPolls":false,"canVotePolls":false,"cover":null,"cover_thumbnail":null,"canSetProfileCover":false,"canEditOwnNickname":false,"bio":null,"canViewBio":true,"canEditBio":false}