{"username":"Drake","displayName":"Drake","avatarUrl":"https://drama.gg/assets/avatars/yLtJa9Tl7r9oC5qT.png","slug":"Drake","joinTime":"2021-10-09T18:32:32+00:00","discussionCount":1,"commentCount":3,"canEdit":false,"canDelete":false,"lastSeenAt":"2021-10-22T03:20:51+00:00","canSuspend":false,"canEditPolls":false,"canStartPolls":false,"canSelfEditPolls":false,"canVotePolls":false,"cover":null,"cover_thumbnail":null,"canSetProfileCover":false,"canEditOwnNickname":false,"bio":null,"canViewBio":true,"canEditBio":false}