{"username":"JakeAndersan","displayName":"JakeAndersan","avatarUrl":"https://drama.gg/assets/avatars/Qoe8BGxA7yciGpcg.png","slug":"JakeAndersan","joinTime":"2021-10-26T04:04:31+00:00","discussionCount":0,"commentCount":41,"canEdit":false,"canDelete":false,"lastSeenAt":"2022-04-15T12:48:45+00:00","canSuspend":false,"canEditPolls":false,"canStartPolls":false,"canSelfEditPolls":false,"canVotePolls":false,"cover":null,"cover_thumbnail":null,"canSetProfileCover":false,"canEditOwnNickname":false,"bio":null,"canViewBio":true,"canEditBio":false}