{"username":"TacticalModz","displayName":"TacticalModz","avatarUrl":"https://drama.gg/assets/avatars/w0MxLvNMmKQUEhn4.png","slug":"TacticalModz","joinTime":"2021-11-29T23:32:48+00:00","discussionCount":0,"commentCount":0,"canEdit":false,"canDelete":false,"lastSeenAt":"2021-11-30T00:03:21+00:00","canSuspend":false,"canEditPolls":false,"canStartPolls":false,"canSelfEditPolls":false,"canVotePolls":false,"cover":null,"cover_thumbnail":null,"canSetProfileCover":false,"canEditOwnNickname":false,"bio":"","canViewBio":true,"canEditBio":false}