{"username":"SouthernGod","displayName":"SouthernGod","avatarUrl":"https://drama.gg/assets/avatars/10mrwU7NZP6u3kxy.png","slug":"SouthernGod","joinTime":"2021-12-28T19:51:53+00:00","discussionCount":0,"commentCount":0,"canEdit":false,"canDelete":false,"lastSeenAt":"2021-12-28T19:52:04+00:00","canSuspend":false,"canEditPolls":false,"canStartPolls":false,"canSelfEditPolls":false,"canVotePolls":false,"cover":null,"cover_thumbnail":null,"canSetProfileCover":false,"canEditOwnNickname":false,"bio":null,"canViewBio":true,"canEditBio":false}