{"username":"DevXo","displayName":"DevXo","avatarUrl":"https://drama.gg/assets/avatars/bKacRbODryRUuxZE.png","slug":"DevXo","joinTime":"2022-02-02T17:40:45+00:00","discussionCount":2,"commentCount":54,"canEdit":false,"canDelete":false,"lastSeenAt":"2022-11-11T16:07:56+00:00","canSuspend":false,"canEditPolls":false,"canStartPolls":false,"canSelfEditPolls":false,"canVotePolls":false,"cover":null,"cover_thumbnail":null,"canSetProfileCover":false,"canEditOwnNickname":false,"bio":null,"canViewBio":true,"canEditBio":false}