{"username":"randomboi6969","displayName":"randomboi6969","avatarUrl":"https://drama.gg/assets/avatars/nIRxWboV1RZquC0I.png","slug":"randomboi6969","joinTime":"2022-02-19T04:31:13+00:00","discussionCount":0,"commentCount":9,"canEdit":false,"canDelete":false,"lastSeenAt":"2022-02-19T07:06:22+00:00","canSuspend":false,"canEditPolls":false,"canStartPolls":false,"canSelfEditPolls":false,"canVotePolls":false,"cover":null,"cover_thumbnail":null,"canSetProfileCover":false,"canEditOwnNickname":false,"bio":null,"canViewBio":true,"canEditBio":false}