{"username":"SURAJ_GAMER","displayName":"SURAJ_GAMER","avatarUrl":"https://drama.gg/assets/avatars/a3R8bFS0EpLO76kZ.png","slug":"SURAJ_GAMER","joinTime":"2022-05-16T07:19:36+00:00","discussionCount":0,"commentCount":0,"canEdit":false,"canDelete":false,"lastSeenAt":"2022-05-18T05:50:25+00:00","canSuspend":false,"canEditPolls":false,"canStartPolls":false,"canSelfEditPolls":false,"canVotePolls":false,"cover":null,"cover_thumbnail":null,"canSetProfileCover":false,"canEditOwnNickname":false,"bio":null,"canViewBio":true,"canEditBio":false}