{"username":"_Cisco","displayName":"_Cisco","avatarUrl":"https://drama.gg/assets/avatars/t74CG4NImLiIPbK1.png","slug":"_Cisco","joinTime":"2022-10-23T21:34:30+00:00","discussionCount":0,"commentCount":0,"canEdit":false,"canDelete":false,"lastSeenAt":"2022-10-23T21:36:43+00:00","canSuspend":false,"canEditPolls":false,"canStartPolls":false,"canSelfEditPolls":false,"canVotePolls":false,"cover":null,"cover_thumbnail":null,"canSetProfileCover":false,"canEditOwnNickname":false,"bio":null,"canViewBio":true,"canEditBio":false}