{"username":"Kolama_PlurrYT","displayName":"Kolama_PlurrYT","avatarUrl":"https://drama.gg/assets/avatars/AayGDgA3OXBPr2r5.png","slug":"Kolama_PlurrYT","joinTime":"2023-05-24T18:55:32+00:00","discussionCount":0,"commentCount":27,"canEdit":false,"canDelete":false,"lastSeenAt":"2023-10-14T09:19:28+00:00","canSuspend":false,"canEditPolls":false,"canStartPolls":false,"canSelfEditPolls":false,"canVotePolls":false,"cover":null,"cover_thumbnail":null,"canSetProfileCover":false,"canEditOwnNickname":false,"bio":null,"canViewBio":true,"canEditBio":false}