{"username":"pt97","displayName":"pt97","avatarUrl":"https://drama.gg/assets/avatars/HfZLj3X4WNxc3E8Z.png","slug":"pt97","joinTime":"2023-08-26T12:50:24+00:00","discussionCount":0,"commentCount":0,"canEdit":false,"canDelete":false,"lastSeenAt":"2023-08-26T13:18:22+00:00","canSuspend":false,"canEditPolls":false,"canStartPolls":false,"canSelfEditPolls":false,"canVotePolls":false,"cover":null,"cover_thumbnail":null,"canSetProfileCover":false,"canEditOwnNickname":false,"bio":null,"canViewBio":true,"canEditBio":false}